main/__init__.py
main/hash.py
main/key.py
main/network_tools.py
kaede_scure_lib-1.0.0.dist-info/METADATA
kaede_scure_lib-1.0.0.dist-info/WHEEL
kaede_scure_lib-1.0.0.dist-info/top_level.txt
kaede_scure_lib-1.0.0.dist-info/RECORD
