Metadata-Version: 2.2
Name: kaede_scure_lib
Version: 1.0.0
Summary: A custom security library with hashing, encryption, and network tools
Home-page: https://github.com/Wadakaede/security_lib.git
Author: Wadakaede
Author-email: kaede04079642@outlook.com
Classifier: Programming Language :: Python :: 3
Classifier: License :: OSI Approved :: MIT License
Classifier: Operating System :: OS Independent
Requires-Python: >=3.6
Requires-Dist: cryptography>=3.4.8
Dynamic: author
Dynamic: author-email
Dynamic: classifier
Dynamic: home-page
Dynamic: requires-dist
Dynamic: requires-python
Dynamic: summary
